setup.py
parallel_code/__init__.py
parallel_code/parallel_integrate.py
parallel_integral.egg-info/PKG-INFO
parallel_integral.egg-info/SOURCES.txt
parallel_integral.egg-info/dependency_links.txt
parallel_integral.egg-info/top_level.txt