Metadata-Version: 2.1
Name: parallel-integral
Version: 0.0.1
Summary: A package to make integrals in parallel
Author: God, the one who wrote everything
